mmdc/__init__.py
mmdc/cli.py
mmdc/core/__init__.py
mmdc/core/converter.py
mmdc/core/exceptions.py
mmdc/core/types.py
mmdc/core/validator.py
mmdc/processors/__init__.py
mmdc/processors/batch.py
mmdc/processors/markdown.py
mmdc/utils/__init__.py
mmdc/utils/file_utils.py
mmdc/utils/logging_utils.py
mmdc/utils/shortcuts.py
mmdc/utils/simple.py
node_modules/katex/src/fonts/generate_fonts.py
node_modules/katex/src/metrics/extract_tfms.py
node_modules/katex/src/metrics/extract_ttfs.py
node_modules/katex/src/metrics/format_json.py
node_modules/katex/src/metrics/parse_tfm.py
pymmdc-0.1.0.dist-info/licenses/LICENSE
pymmdc-0.1.0.dist-info/METADATA
pymmdc-0.1.0.dist-info/WHEEL
pymmdc-0.1.0.dist-info/entry_points.txt
pymmdc-0.1.0.dist-info/top_level.txt
pymmdc-0.1.0.dist-info/RECORD
