Metadata-Version: 2.4
Name: pymmdc
Version: 0.1.0
Summary: Pure Python Mermaid Diagram Converter with robust error handling
Home-page: https://pypi.org/project/pymmdc/
Author: wambua
Author-email: swskye17@gmail.com
License: GNU v3
Keywords: mmdc,pymmdc,mermaid,png,mermaid_diagram
Classifier: Environment :: Console
Classifier: Natural Language :: English
Classifier: Operating System :: OS Independent
Classifier: Programming Language :: Python
Classifier: Programming Language :: Python :: 3 :: Only
Classifier: Programming Language :: Python :: 3.12
Classifier: Programming Language :: Python :: 3.13
Requires-Python: >=3.12
License-File: LICENSE
Requires-Dist: setuptools
Requires-Dist: wheel
Requires-Dist: argparse
Dynamic: author
Dynamic: author-email
Dynamic: classifier
Dynamic: description
Dynamic: description-content-type
Dynamic: home-page
Dynamic: keywords
Dynamic: license
Dynamic: license-file
Dynamic: requires-dist
Dynamic: requires-python
Dynamic: summary
